openskl/__init__.py
openskl/util.py
openskl-0.0.1.dist-info/METADATA
openskl-0.0.1.dist-info/WHEEL
openskl-0.0.1.dist-info/top_level.txt
openskl-0.0.1.dist-info/RECORD
