Metadata-Version: 2.1
Name: openskl
Version: 0.0.1
Summary: OpenSKL Python Library
Author: OpenSKL Team
Author-email: silveryfu@gmail.com
License: Apache License, Version 2.0
Requires-Python: >=3.8
Requires-Dist: openai
Requires-Dist: pyyaml
Requires-Dist: numpy
Requires-Dist: langchain
